lhammai_cli/__init__.py
lhammai_cli/history.py
lhammai_cli/main.py
lhammai_cli/py.typed
lhammai_cli/schema.py
lhammai_cli/settings.py
lhammai_cli/utils/__init__.py
lhammai_cli/utils/llm_utils.py
lhammai_cli/utils/logging.py
lhammai_cli-0.1.0a10.dist-info/WHEEL
lhammai_cli-0.1.0a10.dist-info/entry_points.txt
lhammai_cli-0.1.0a10.dist-info/METADATA
lhammai_cli-0.1.0a10.dist-info/RECORD
