Metadata-Version: 2.3
Name: lhammai-cli
Version: 0.1.0a10
Summary: Interact with any LLM from your terminal
Author: Dimitris Poulopoulos
Author-email: Dimitris Poulopoulos <dimitris.a.poulopoulos@gmail.com>
Requires-Dist: click>=8.2.1
Requires-Dist: dotenv>=0.9.9
Requires-Dist: halo>=0.0.31
Requires-Dist: loguru>=0.7.3
Requires-Dist: pydantic-settings>=2.10.1
Requires-Dist: rich>=14.1.0
Requires-Dist: any-llm-sdk[ollama]>=0.16.0 ; extra == 'ollama'
Requires-Python: >=3.13
Project-URL: Issues, https://github.com/dpoulopoulos/lhammai-cli/issues
Project-URL: Source, https://github.com/dpoulopoulos/lhammai-cli
Provides-Extra: ollama
